hsmkey/__init__.py
hsmkey/algorithms.py
hsmkey/config.py
hsmkey/exceptions.py
hsmkey/jwk_integration.py
hsmkey/py.typed
hsmkey/session.py
hsmkey/keys/__init__.py
hsmkey/keys/base.py
hsmkey/keys/ec.py
hsmkey/keys/ed25519.py
hsmkey/keys/ed448.py
hsmkey/keys/rsa.py
hsmkey-0.2.0.dist-info/licenses/LICENSE
hsmkey-0.2.0.dist-info/WHEEL
hsmkey-0.2.0.dist-info/METADATA
hsmkey-0.2.0.dist-info/RECORD
