Metadata-Version: 2.4
Name: hsmkey
Version: 0.2.0
Summary: HSM-backed cryptographic keys compatible with Python cryptography library
Keywords: hsm,pkcs11,cryptography,security,signing
Author-email: Kushal Das <mail@kushaldas.in>
Requires-Python: >=3.10
Classifier: Development Status :: 3 - Alpha
Classifier: Intended Audience :: Developers
Classifier: Programming Language :: Python :: 3
Classifier: Programming Language :: Python :: 3.10
Classifier: Programming Language :: Python :: 3.11
Classifier: Programming Language :: Python :: 3.12
Classifier: Programming Language :: Python :: 3.13
Classifier: Programming Language :: Python :: 3.14
Classifier: Topic :: Security :: Cryptography
License-File: LICENSE
Requires-Dist: cryptography>=41.0.0
Requires-Dist: python-pkcs11>=0.7.0
Requires-Dist: pytest>=8.0.0 ; extra == "dev"
Requires-Dist: pytest-cov>=4.0.0 ; extra == "dev"
Requires-Dist: ty ; extra == "dev"
Requires-Dist: ruff ; extra == "dev"
Requires-Dist: flit ; extra == "dev"
Requires-Dist: scriv ; extra == "dev"
Requires-Dist: jwcrypto>=1.5.0 ; extra == "dev"
Requires-Dist: sphinx>=7.0.0 ; extra == "docs"
Requires-Dist: sphinx-rtd-theme>=2.0.0 ; extra == "docs"
Requires-Dist: sphinx-autodoc-typehints>=2.0.0 ; extra == "docs"
Requires-Dist: jwcrypto>=1.5.0 ; extra == "jwcrypto"
Project-URL: Documentation, https://hsmkey.readthedocs.io/en/latest/
Project-URL: Source, https://github.com/kushaldas/hsmkey
Provides-Extra: dev
Provides-Extra: docs
Provides-Extra: jwcrypto
